sagemaker_schema_inference_artifacts/__init__.py
sagemaker_schema_inference_artifacts/huggingface/__init__.py
sagemaker_schema_inference_artifacts/huggingface/config.py
sagemaker_schema_inference_artifacts/huggingface/remote_schema_retriever.py
sagemaker_schema_inference_artifacts/huggingface/node_modules/@huggingface/tasks/LICENSE
sagemaker_schema_inference_artifacts/huggingface/node_modules/@huggingface/tasks/README.md
sagemaker_schema_inference_artifacts/huggingface/node_modules/@huggingface/tasks/package.json
sagemaker_schema_inference_artifacts/huggingface/node_modules/@huggingface/tasks/tsconfig.json
sagemaker_schema_inference_artifacts/huggingface/node_modules/@huggingface/tasks/dist/index.cjs
sagemaker_schema_inference_artifacts/huggingface/node_modules/@huggingface/tasks/dist/index.d.ts
sagemaker_schema_inference_artifacts/huggingface/node_modules/@huggingface/tasks/dist/index.js
sagemaker_schema_inference_artifacts/huggingface/node_modules/@huggingface/tasks/src/default-widget-inputs.ts
sagemaker_schema_inference_artifacts/huggingface/node_modules/@huggingface/tasks/src/index.ts
sagemaker_schema_inference_artifacts/huggingface/node_modules/@huggingface/tasks/src/library-to-tasks.ts
sagemaker_schema_inference_artifacts/huggingface/node_modules/@huggingface/tasks/src/model-data.ts
sagemaker_schema_inference_artifacts/huggingface/node_modules/@huggingface/tasks/src/model-libraries-downloads.ts
sagemaker_schema_inference_artifacts/huggingface/node_modules/@huggingface/tasks/src/model-libraries-snippets.ts
sagemaker_schema_inference_artifacts/huggingface/node_modules/@huggingface/tasks/src/model-libraries.ts
sagemaker_schema_inference_artifacts/huggingface/node_modules/@huggingface/tasks/src/pipelines.ts
sagemaker_schema_inference_artifacts/huggingface/node_modules/@huggingface/tasks/src/tokenizer-data.ts
sagemaker_schema_inference_artifacts/huggingface/node_modules/@huggingface/tasks/src/widget-example.ts
sagemaker_schema_inference_artifacts-0.0.5.dist-info/METADATA
sagemaker_schema_inference_artifacts-0.0.5.dist-info/WHEEL
sagemaker_schema_inference_artifacts-0.0.5.dist-info/top_level.txt
sagemaker_schema_inference_artifacts-0.0.5.dist-info/RECORD
