Metadata-Version: 2.1
Name: sagemaker-schema-inference-artifacts
Version: 0.0.5
Summary: Open source library for Hugging Face Task Sample Inputs and Outputs
Home-page: https://github.com/aws/sagemaker-schema-inference-artifacts/
Author: Amazon Web Services
License: Apache License 2.0
Keywords: ML Amazon AWS AI Schema Inference Artifacts
Classifier: Development Status :: 5 - Production/Stable
Classifier: Intended Audience :: Developers
Classifier: Natural Language :: English
Classifier: License :: OSI Approved :: Apache Software License
Classifier: Programming Language :: Python
Classifier: Programming Language :: Python :: 3.8
Classifier: Programming Language :: Python :: 3.9
Classifier: Programming Language :: Python :: 3.10
Requires-Python: >= 3.8
Requires-Dist: json5 >=0.9.22
Provides-Extra: test
Requires-Dist: tox ==3.24.5 ; extra == 'test'
Requires-Dist: flake8 ==4.0.1 ; extra == 'test'
Requires-Dist: pytest ==6.2.5 ; extra == 'test'
Requires-Dist: pytest-cov ==3.0.0 ; extra == 'test'
Requires-Dist: pytest-rerunfailures ==10.2 ; extra == 'test'
Requires-Dist: pytest-timeout ==2.1.0 ; extra == 'test'
Requires-Dist: pytest-xdist ==2.4.0 ; extra == 'test'
Requires-Dist: coverage <6.2,>=5.2 ; extra == 'test'
Requires-Dist: mock ==4.0.3 ; extra == 'test'
Requires-Dist: contextlib2 ==21.6.0 ; extra == 'test'
Requires-Dist: awslogs ==0.14.0 ; extra == 'test'
Requires-Dist: black ==24.3.0 ; extra == 'test'
